nlputils/__init__.py
nlputils/dict_utils.py
nlputils/embedding.py
nlputils/features.py
nlputils/knn_classifier.py
nlputils/ml_utils.py
nlputils/simcoefs.py
nlputils/simmat.py
nlputils/visualize.py
nlputils-1.0.7.dist-info/LICENSE
nlputils-1.0.7.dist-info/METADATA
nlputils-1.0.7.dist-info/WHEEL
nlputils-1.0.7.dist-info/top_level.txt
nlputils-1.0.7.dist-info/RECORD
