Metadata-Version: 2.1
Name: nlputils
Version: 1.0.7
Summary: Natural Language Processing Utility Functions
Home-page: https://github.com/cod3licious/nlputils
Author: cod3licious
Author-email: cod3licious@gmail.com
License: MIT
Keywords: natural language processing machine learning text processing
Platform: UNKNOWN
Classifier: Development Status :: 3 - Alpha
Classifier: Intended Audience :: Science/Research
Classifier: Topic :: Scientific/Engineering :: Artificial Intelligence
Classifier: License :: OSI Approved :: MIT License
Classifier: Programming Language :: Python :: 2
Classifier: Programming Language :: Python :: 2.7
Classifier: Programming Language :: Python :: 3
Classifier: Programming Language :: Python :: 3.4
Classifier: Programming Language :: Python :: 3.5
Classifier: Programming Language :: Python :: 3.6
Requires-Dist: future
Requires-Dist: numpy
Requires-Dist: scipy
Requires-Dist: matplotlib
